nonebot_plugin_pjsk-0.4.1.dist-info/METADATA
nonebot_plugin_pjsk-0.4.1.dist-info/WHEEL
nonebot_plugin_pjsk-0.4.1.dist-info/entry_points.txt
nonebot_plugin_pjsk-0.4.1.dist-info/licenses/LICENSE
nonebot_plugin_pjsk/__init__.py
nonebot_plugin_pjsk/__main__.py
nonebot_plugin_pjsk/config.py
nonebot_plugin_pjsk/render.py
nonebot_plugin_pjsk/resource.py
nonebot_plugin_pjsk/templates/help.html.jinja
nonebot_plugin_pjsk/templates/sticker.svg.jinja
nonebot_plugin_pjsk/templates/sticker_grid.html.jinja
nonebot_plugin_pjsk/utils.py
nonebot_plugin_pjsk-0.4.1.dist-info/RECORD
