Metadata-Version: 2.1
Name: nonebot-plugin-pjsk
Version: 0.4.1
Summary: Project Sekai Sticker Creator for NoneBot2.
Keywords: pjsk,nonebot2,plugin
Author-Email: Agnes_Digital <Z735803792@163.com>, student_2333 <lgc2333@126.com>
License: MIT
Classifier: License :: OSI Approved :: MIT License
Classifier: Programming Language :: Python
Classifier: Programming Language :: Python :: 3
Classifier: Programming Language :: Python :: 3.9
Classifier: Programming Language :: Python :: 3.10
Classifier: Programming Language :: Python :: 3.11
Classifier: Operating System :: OS Independent
Project-URL: homepage, https://github.com/lgc-NB2Dev/nonebot-plugin-pjsk
Requires-Python: <=4,>=3.9
Requires-Dist: nonebot2>=2.3.1
Requires-Dist: httpx>=0.27.0
Requires-Dist: anyio>=4.4.0
Requires-Dist: nonebot-plugin-alconna>=0.48.0
Requires-Dist: nonebot-plugin-htmlrender>=0.3.2
Requires-Dist: jinja2>=3.1.4
Requires-Dist: yarl>=1.9.4
